AUTHORS.rst
CONTRIBUTING.rst
HISTORY.rst
LICENSE
MANIFEST.in
README.rst
setup.cfg
setup.py
docs/Makefile
docs/authors.rst
docs/conf.py
docs/contributing.rst
docs/history.rst
docs/index.rst
docs/installation.rst
docs/make.bat
docs/readme.rst
docs/usage.rst
docs/_build/html/_static/file.png
docs/_build/html/_static/minus.png
docs/_build/html/_static/plus.png
manga_manager/__init__.py
manga_manager/cli.py
manga_manager/manga_manager.py
manga_manager/util.py
manga_manager.egg-info/PKG-INFO
manga_manager.egg-info/SOURCES.txt
manga_manager.egg-info/dependency_links.txt
manga_manager.egg-info/entry_points.txt
manga_manager.egg-info/not-zip-safe
manga_manager.egg-info/requires.txt
manga_manager.egg-info/top_level.txt
manga_manager/provider/__init__.py
manga_manager/provider/mangakakalot.py
manga_manager/provider/provider.py
tests/__init__.py
tests/test_manga_manager.py