Metadata-Version: 1.2
Name: manga-manager
Version: 0.1.0
Summary: A tool for downloading and reading manga.
Home-page: https://github.com/tkmcclellan/manga_manager
Author: Tyler Kyle McClellan
Author-email: the8bitgamer11@gmail.com
License: MIT license
Keywords: manga_manager
Platform: UNKNOWN
Classifier: Development Status :: 2 - Pre-Alpha
Classifier: Intended Audience :: Developers
Classifier: License :: OSI Approved :: MIT License
Classifier: Natural Language :: English
Classifier: Programming Language :: Python :: 3
Classifier: Programming Language :: Python :: 3.5
Classifier: Programming Language :: Python :: 3.6
Classifier: Programming Language :: Python :: 3.7
Classifier: Programming Language :: Python :: 3.8
Requires-Python: >=3.5
